greengrasssdk/IoTDataPlane.py
greengrasssdk/Lambda.py
greengrasssdk/SecretsManager.py
greengrasssdk/__init__.py
greengrasssdk/client.py
greengrasssdk/stream_manager/__init__.py
greengrasssdk/stream_manager/exceptions.py
greengrasssdk/stream_manager/streammanagerclient.py
greengrasssdk/stream_manager/util.py
greengrasssdk/stream_manager/utilinternal.py
greengrasssdk/stream_manager/data/__init__.py
greengrasssdk/utils/__init__.py
greengrasssdk/utils/testing.py
greengrasssdk-1.6.1.dist-info/LICENSE
greengrasssdk-1.6.1.dist-info/METADATA
greengrasssdk-1.6.1.dist-info/WHEEL
greengrasssdk-1.6.1.dist-info/top_level.txt
greengrasssdk-1.6.1.dist-info/RECORD
